{
  "traveler-in-time": {
    "artists": "Dimatis & Elvya",
    "title": "Traveler In time",
    "description": "Who wouldn't want to travel back or forward in time? I have the pleasure to bring you another song with Elvya this time with a time traveler theme, get ready to be delighted with a chill-type beat using sparkly and enveloping sounds that we could probably hear during a time teleportation while everything stops around you 💫. I came up with the instrumental of this song as an idea of mine almost 3 years ago but the result never convinced me so I never released it until talking to Elvya I showed her the demo and she added that magic missing, Now it comes alive thanks to her amazing vocals as always 💜.",
    "tracks": [
      "traveler-in-time",
      "traveler-in-time-instrumental"
    ],
    "cover": "traveler-in-time",
    "type": "Single",
    "date": "2022-11-25T00:00:00.000",
    "person": ["Dimatis", "Elvya"]
  },
  "experiences": {
    "artists": "Dimatis",
    "title": "Experiences",
    "description": "Hello, I am very excited to present my first album 'Experiences' this album represents some feelings of my experiences lived during 2019, I hope you like it.",
    "tracks": [
      "experiences",
      "grief",
      "moments-together",
      "now",
      "overcoming",
      "serenity",
      "unusual"
    ],
    "cover": "experiences-album",
    "type": "Album",
    "date": "2020-01-24T00:00:00.000",
    "person": ["Dimatis"],
    "fanlink": {
      "download": true,
      "dark": false,
      "links": {
        "spotify": "https://open.spotify.com/album/2nCLG8xdGCenV30yUBM0O7",
        "soundcloud": "https://soundcloud.com/dimatis/sets/experiences",
        "youtube": "https://www.youtube.com/playlist?list=PLrYFLU1XWSM1HbvCfVPT5kW2nbr5-xCnf",
        "itunes": "https://music.apple.com/us/album/experiences/1495650794?app=itunes&ls=1",
        "apple": "https://music.apple.com/us/album/experiences/1495650794?app=music&ls=1",
        "bandcamp": "https://dimatis.bandcamp.com/album/experiences",
        "deezer": "https://www.deezer.com/en/album/128070352",
        "tidal": "https://tidal.com/browse/album/128864931",
        "amazon": "https://www.amazon.com/Experiences-Dimatis/dp/B0845QPK2R",
        "netease": "https://music.163.com/#/album?id=85146628"
      }
    }
  },
  "floating": {
    "artists": "Dimatis",
    "title": "Floating",
    "description": "Floating is my first EP ever! 🎶 it contains 4 tracks in different genres.",
    "tracks": [
      "mists",
      "floating",
      "shades",
      "what-awaits-us"
    ],
    "cover": "floating-ep",
    "type": "EP",
    "date": "2019-01-28T00:00:00.000",
    "person": ["Dimatis"],
    "fanlink": {
      "download": true,
      "dark": false,
      "links": {
        "spotify": "https://open.spotify.com/album/0o0UjObCp5ZizH3tDblWZ3",
        "soundcloud": "https://soundcloud.com/dimatis/sets/floating-ep",
        "youtube": "https://www.youtube.com/playlist?list=PLrYFLU1XWSM04jOkQJrtQ7HnhqQfwdQot",
        "itunes": "https://music.apple.com/us/album/floating-ep/1451828741?app=itunes&ls=1",
        "apple": "https://music.apple.com/us/album/floating-ep/1451828741?app=music&ls=1",
        "bandcamp": "https://dimatis.bandcamp.com/album/floating-ep",
        "deezer": "https://www.deezer.com/en/album/86746842",
        "tidal": "https://tidal.com/browse/album/103796097",
        "netease": "https://music.163.com/#/album?id=78762872"
      }
    }
  },
  "moonlit-lover": {
    "artists": "Dimatis",
    "title": "Moonlit Lover",
    "description": "Moonlit lover has a chillstep track and the piano version, you can relax listening to the melodies under the moonlight. ❤",
    "tracks": [
      "moonlit-lover",
      "moonlit-lover-piano"
    ],
    "cover": "moonlit-lover",
    "type": "Single",
    "date": "2018-08-01T00:00:00.000",
    "person": ["Dimatis"]
  }
}
